.gitignore
README.rst
pyproject.toml
setup.cfg
setup.py
docs/Makefile
docs/conf.py
docs/index.rst
py_gql_test_client/__init__.py
py_gql_test_client/async_client.py
py_gql_test_client/base.py
py_gql_test_client/client.py
py_gql_test_client/exceptions.py
py_gql_test_client/response_encoders.py
py_gql_test_client.egg-info/PKG-INFO
py_gql_test_client.egg-info/SOURCES.txt
py_gql_test_client.egg-info/dependency_links.txt
py_gql_test_client.egg-info/requires.txt
py_gql_test_client.egg-info/top_level.txt
py_gql_test_client/tests/__init__.py
py_gql_test_client/tests/test_async_client.py
py_gql_test_client/tests/test_graphql_base.py
py_gql_test_client/tests/test_graphql_client.py
py_gql_test_client/tests/test_response_encoders.py