Metadata-Version: 2.1
Name: py-gql-test-client
Version: 1.0.1
Summary: Forked and updated version of https://pypi.org/project/gqlclient/
Home-page: UNKNOWN
License: UNKNOWN
Platform: UNKNOWN
Classifier: Programming Language :: Python
Classifier: Programming Language :: Python :: 3
Classifier: Programming Language :: Python :: 3.7
Requires-Python: >=3.6
Provides-Extra: async
